lambre/__init__.py
lambre/download.py
lambre/metric.py
lambre/parse_utils.py
lambre/relation_map
lambre/rule_links
lambre/rule_utils.py
lambre/score_utils_chaudhary.py
lambre/score_utils_pratapa.py
lambre/visualize.py
lambre/html_templates/footer.html
lambre/html_templates/header.html
lambre-2.0.2.dist-info/METADATA
lambre-2.0.2.dist-info/WHEEL
lambre-2.0.2.dist-info/entry_points.txt
lambre-2.0.2.dist-info/top_level.txt
lambre-2.0.2.dist-info/RECORD
