Metadata-Version: 2.1
Name: lambre
Version: 2.0.2
Summary: a tool to measure the grammatical well-formedness of multilingual texts
Home-page: https://github.com/adithya7/lambre
Author: Adithya Pratapa, Antonios Anastasopoulos, Shruti Rijhwani, Aditi Chaudhary, David R. Mortensen, Graham Neubig and Yulia Tsvetkov
License: UNKNOWN
Project-URL: Bug Tracker, https://github.com/adithya7/lambre/issues
Keywords: multilingual,text-generation,evaluation
Platform: UNKNOWN
Classifier: Programming Language :: Python :: 3.6
Classifier: License :: OSI Approved :: MIT License
Requires-Python: >=3.6
Requires-Dist: stanza (==1.3.0)
Requires-Dist: pyconll
Requires-Dist: ipymarkup
Requires-Dist: scipy
